darkpy/__init__.py
darkpy/date/__init__.py
darkpy/date/dtget.py
darkpy/date/dtmath.py
darkpy/math/__init__.py
darkpy/math/statistic.py
darkpy-0.1.7.dist-info/METADATA
darkpy-0.1.7.dist-info/WHEEL
darkpy-0.1.7.dist-info/top_level.txt
darkpy-0.1.7.dist-info/RECORD
