Metadata-Version: 2.1
Name: darkpy
Version: 0.1.7
Summary: DarkPy is a Python library which brings some useful calculations
